{"glossaryBindings":[],"lineWrap":true,"defaultValue":"","length":0,"description":"","isGlossaryDefinition":false,"type":"MetaDataStringInfo","isList":false,"multilanguage":false,"stencilsetBindings":[{"namespace":"http://b3mn.org/stencilset/bpmn2.0conversation#","stencil":"BPMNDiagram","order":0},{"namespace":"http://b3mn.org/stencilset/epc#","stencil":"Diagram","order":0},{"namespace":"http://b3mn.org/stencilset/bpmn2.0choreography#","stencil":"BPMNDiagram","order":0},{"namespace":"http://b3mn.org/stencilset/bpmn2.0#","stencil":"BPMNDiagram","order":0},{"namespace":"http://www.signavio.com/stencilsets/processmap#","stencil":"Diagram","order":0}],"readonly":false,"name":"Process target","id":"processgoal"}